dotdict_parser.cpython-38-i386-linux-gnu.so
dotdict_parser-0.7.2.dist-info/METADATA
dotdict_parser-0.7.2.dist-info/WHEEL
dotdict_parser-0.7.2.dist-info/RECORD
dotdict_parser-0.7.2.dist-info/top_level.txt
