Metadata-Version: 2.1
Name: dotdict_parser
Version: 0.7.2
Summary: A unified path parser in C for Python
Author: Risto Kowaczewski
License: GPL-3
Classifier: Programming Language :: Python :: 3
Classifier: Programming Language :: C
Classifier: License :: OSI Approved :: GNU General Public License v3 or later (GPLv3+)
Classifier: Operating System :: OS Independent
Requires-Python: >=3.8
